fmu_manipulation_toolbox/__init__.py
fmu_manipulation_toolbox/__main__.py
fmu_manipulation_toolbox/__version__.py
fmu_manipulation_toolbox/assembly.py
fmu_manipulation_toolbox/checker.py
fmu_manipulation_toolbox/container.py
fmu_manipulation_toolbox/gui.py
fmu_manipulation_toolbox/gui_style.py
fmu_manipulation_toolbox/help.py
fmu_manipulation_toolbox/operations.py
fmu_manipulation_toolbox/remoting.py
fmu_manipulation_toolbox/split.py
fmu_manipulation_toolbox/version.py
fmu_manipulation_toolbox/cli/__init__.py
fmu_manipulation_toolbox/cli/fmucontainer.py
fmu_manipulation_toolbox/cli/fmusplit.py
fmu_manipulation_toolbox/cli/fmutool.py
fmu_manipulation_toolbox/cli/utils.py
fmu_manipulation_toolbox/resources/checkbox-checked-disabled.png
fmu_manipulation_toolbox/resources/checkbox-checked-hover.png
fmu_manipulation_toolbox/resources/checkbox-checked.png
fmu_manipulation_toolbox/resources/checkbox-unchecked-disabled.png
fmu_manipulation_toolbox/resources/checkbox-unchecked-hover.png
fmu_manipulation_toolbox/resources/checkbox-unchecked.png
fmu_manipulation_toolbox/resources/container.png
fmu_manipulation_toolbox/resources/drop_fmu.png
fmu_manipulation_toolbox/resources/fmu.png
fmu_manipulation_toolbox/resources/fmu_manipulation_toolbox.png
fmu_manipulation_toolbox/resources/help.png
fmu_manipulation_toolbox/resources/icon-round.png
fmu_manipulation_toolbox/resources/icon.png
fmu_manipulation_toolbox/resources/icon_fmu.png
fmu_manipulation_toolbox/resources/license.txt
fmu_manipulation_toolbox/resources/mask.png
fmu_manipulation_toolbox/resources/model.png
fmu_manipulation_toolbox/resources/darwin64/container.dylib
fmu_manipulation_toolbox/resources/fmi-2.0/fmi2Annotation.xsd
fmu_manipulation_toolbox/resources/fmi-2.0/fmi2AttributeGroups.xsd
fmu_manipulation_toolbox/resources/fmi-2.0/fmi2ModelDescription.xsd
fmu_manipulation_toolbox/resources/fmi-2.0/fmi2ScalarVariable.xsd
fmu_manipulation_toolbox/resources/fmi-2.0/fmi2Type.xsd
fmu_manipulation_toolbox-1.9.1.3.dist-info/licenses/LICENSE.txt
fmu_manipulation_toolbox-1.9.1.3.dist-info/METADATA
fmu_manipulation_toolbox-1.9.1.3.dist-info/WHEEL
fmu_manipulation_toolbox-1.9.1.3.dist-info/entry_points.txt
fmu_manipulation_toolbox-1.9.1.3.dist-info/top_level.txt
fmu_manipulation_toolbox-1.9.1.3.dist-info/RECORD
